setup.cfg
setup.py
fastats_privates.egg-info/PKG-INFO
fastats_privates.egg-info/SOURCES.txt
fastats_privates.egg-info/dependency_links.txt
fastats_privates.egg-info/requires.txt
fastats_privates.egg-info/top_level.txt
privates/__init__.py
privates/_version.py
privates/mutations.py
privates/named_struct.py
privates/core/__init__.py
privates/core/base.py
privates/core/dict_struct.py
privates/core/errors.py