Metadata-Version: 1.1
Name: fastats-privates
Version: 2018.1rc0
Summary: A python library using private/hidden python language features
Home-page: https://github.com/fastats/privates
Author: Fastats Developers
Author-email: fastats@googlegroups.com
License: UNKNOWN
Keywords: python helpers utils internals
Platform: UNKNOWN
Classifier: Development Status :: 4 - Beta
Classifier: Intended Audience :: Developers
Classifier: Intended Audience :: Science/Research
Classifier: Operating System :: OS Independent
Classifier: License :: Freely Distributable
Classifier: License :: Freeware
Classifier: Programming Language :: Python :: 3
Classifier: Programming Language :: Python :: 3 :: Only
Classifier: Programming Language :: Python :: 3.6
